zep_python/__init__.py
zep_python/base_client.py
zep_python/client.py
zep_python/core/__init__.py
zep_python/core/api_error.py
zep_python/core/client_wrapper.py
zep_python/core/datetime_utils.py
zep_python/core/file.py
zep_python/core/http_client.py
zep_python/core/jsonable_encoder.py
zep_python/core/pydantic_utilities.py
zep_python/core/query_encoder.py
zep_python/core/remove_none_from_dict.py
zep_python/core/request_options.py
zep_python/environment.py
zep_python/errors/__init__.py
zep_python/errors/bad_request_error.py
zep_python/errors/conflict_error.py
zep_python/errors/internal_server_error.py
zep_python/errors/not_found_error.py
zep_python/external_clients/memory.py
zep_python/external_clients/user.py
zep_python/memory/__init__.py
zep_python/memory/client.py
zep_python/py.typed
zep_python/types/__init__.py
zep_python/types/api_error.py
zep_python/types/fact.py
zep_python/types/fact_rating_examples.py
zep_python/types/fact_rating_instruction.py
zep_python/types/fact_response.py
zep_python/types/memory.py
zep_python/types/message.py
zep_python/types/message_list_response.py
zep_python/types/role_type.py
zep_python/types/search_scope.py
zep_python/types/search_type.py
zep_python/types/session.py
zep_python/types/session_fact_rating_examples.py
zep_python/types/session_fact_rating_instruction.py
zep_python/types/session_list_response.py
zep_python/types/session_search_response.py
zep_python/types/session_search_result.py
zep_python/types/success_response.py
zep_python/types/summary.py
zep_python/types/user.py
zep_python/types/user_list_response.py
zep_python/user/__init__.py
zep_python/user/client.py
zep_python/version.py
zep_python-2.0.1.dist-info/METADATA
zep_python-2.0.1.dist-info/WHEEL
zep_python-2.0.1.dist-info/RECORD
